metastim/DBSLead-smry.csv
metastim/__init__.py
metastim/axon_ann.py
metastim/field_ann.py
metastim/lead.py
metastim/lead_selector.py
metastim/utils.py
metastim/validations.py
metastim/visualization.py
metastim/axon-ann-model/ann-axon-input-std.bin
metastim/axon-ann-model/ann-axon-settings.json
metastim/axon-ann-model/ann-axon-weights.h5
metastim/field-ann-models/ann-field-ec1-input-std.bin
metastim/field-ann-models/ann-field-ec1-settings.json
metastim/field-ann-models/ann-field-ec1-weights.h5
metastim/field-ann-models/ann-field-ec2-input-std.bin
metastim/field-ann-models/ann-field-ec2-settings.json
metastim/field-ann-models/ann-field-ec2-weights.h5
metastim/field-ann-models/ann-field-ec3-input-std.bin
metastim/field-ann-models/ann-field-ec3-settings.json
metastim/field-ann-models/ann-field-ec3-weights.h5
metastim/field-ann-models/ann-field-ec4-input-std.bin
metastim/field-ann-models/ann-field-ec4-settings.json
metastim/field-ann-models/ann-field-ec4-weights.h5
metastim/field-ann-models/ann-field-ec5-input-std.bin
metastim/field-ann-models/ann-field-ec5-settings.json
metastim/field-ann-models/ann-field-ec5-weights.h5
metastim/field-ann-models/ann-field-ec6-input-std.bin
metastim/field-ann-models/ann-field-ec6-settings.json
metastim/field-ann-models/ann-field-ec6-weights.h5
metastim/field-ann-models/ann-field-ec7-input-std.bin
metastim/field-ann-models/ann-field-ec7-settings.json
metastim/field-ann-models/ann-field-ec7-weights.h5
metastim/field-ann-models/ann-field-ec8-input-std.bin
metastim/field-ann-models/ann-field-ec8-settings.json
metastim/field-ann-models/ann-field-ec8-weights.h5
metastim_beta_3-0.0.3.dist-info/LICENSE
metastim_beta_3-0.0.3.dist-info/METADATA
metastim_beta_3-0.0.3.dist-info/WHEEL
metastim_beta_3-0.0.3.dist-info/top_level.txt
metastim_beta_3-0.0.3.dist-info/RECORD
